exoheat/Flask4LaTex.py
exoheat/LocalisationData.py
exoheat/Matherials.py
exoheat/Walls.py
exoheat/__init__.py
exoheat-0.1.0.dist-info/licenses/license ru.txt
exoheat-0.1.0.dist-info/licenses/license.txt
exoheat-examples/3D_House_Plot.py
exoheat-examples/Home_class.py
exoheat-examples/Home_example.py
exoheat-examples/LocalisationData.py
exoheat-examples/Matherials.py
exoheat-examples/go_report_exmpl.py
exoheat-examples/Пример1 Теплоперадачи расчет потерь.py
exoheat-examples/Пример2 Инфильтрации расчет потерь.py
exoheat-examples/Пример3 Все потери.py
exoheat-examples/Пример41 Домик tuple.py
exoheat-examples/Пример42 Домик tpl class.py
exoheat-examples/Пример43 Домик tpl class pandas.py
exoheat-examples/Пример43 Домик tpl pandas.py
exoheat-0.1.0.dist-info/METADATA
exoheat-0.1.0.dist-info/WHEEL
exoheat-0.1.0.dist-info/top_level.txt
exoheat-0.1.0.dist-info/RECORD
