Metadata-Version: 2.4
Name: exoheat
Version: 0.1.0
Summary: A package for heat calculation
Author-email: Sergei <srg100@list.ru>
Classifier: Development Status :: 3 - Alpha
Classifier: Intended Audience :: Developers
Classifier: License :: OSI Approved :: MIT License
Classifier: Operating System :: OS Independent
Classifier: Programming Language :: Python :: 3
Classifier: Programming Language :: Python :: 3.7
Classifier: Programming Language :: Python :: 3.8
Classifier: Programming Language :: Python :: 3.9
Classifier: Programming Language :: Python :: 3.10
Requires-Python: >=3.7
License-File: license ru.txt
License-File: license.txt
Requires-Dist: Flask>=2.0.0
Requires-Dist: numpy>=1.21.0
Requires-Dist: pandas>=1.3.0
Provides-Extra: dev
Requires-Dist: pytest>=6.0; extra == "dev"
Requires-Dist: black; extra == "dev"
Requires-Dist: flake8; extra == "dev"
Dynamic: license-file
